[
  {
    "Id": "285e75a0062240e39aae3b609654a55c",
    "Email": "6622954@gmail.com",
    "UserId": "",
    "Asin": "B07H3GJNBW",
    "Title": "High Pressure Shower Head - Anti-Clogging Silicone Nozzles - 2.5 GPM Removable Rest...",
    "PriceSeen": 43.99,
    "ImageUrl": "https://m.media-amazon.com/images/I/71MZyIyuBfL._AC_UF480,480_SR480,480_.jpg",
    "Url": "",
    "RecordType": "RelatedProduct",
    "PrimaryAsin": "",
    "Source": "",
    "GroupId": "00000000-0000-0000-0000-000000000000",
    "TimestampUtc": "2025-11-17T23:13:54.0794752Z",
    "IpAddress": "::1"
  },
  {
    "Id": "10fec782c32846c6ba6601d4ba718b3d",
    "Email": "6622954@gmail.com",
    "UserId": "",
    "Asin": "B0DN6DBL2G",
    "Title": "Shower Head High Pressure Rain Premium Quality Luxury Design Anti-Clogging Silicone...",
    "PriceSeen": 17.99,
    "ImageUrl": "https://m.media-amazon.com/images/I/61EW6Y\u002ByKmL._AC_UF480,480_SR480,480_.jpg",
    "Url": "",
    "RecordType": "RelatedProduct",
    "PrimaryAsin": "",
    "Source": "",
    "GroupId": "00000000-0000-0000-0000-000000000000",
    "TimestampUtc": "2025-11-17T23:13:54.0823198Z",
    "IpAddress": "::1"
  },
  {
    "Id": "8d5cd24bdc794856abf7b649696685ee",
    "Email": "6622954@gmail.com",
    "UserId": "",
    "Asin": "B08QR7PGCT",
    "Title": "Heatsistence-Luxury Rainfall Shower Head - High-Pressure showerhead Jets, rain\u2026",
    "PriceSeen": 22.99,
    "ImageUrl": "https://m.media-amazon.com/images/I/81yPbiYLIHL._AC_UF480,480_SR480,480_.jpg",
    "Url": "",
    "RecordType": "RelatedProduct",
    "PrimaryAsin": "",
    "Source": "",
    "GroupId": "00000000-0000-0000-0000-000000000000",
    "TimestampUtc": "2025-11-17T23:13:54.0823781Z",
    "IpAddress": "::1"
  },
  {
    "Id": "b3611184be6d4b468707afb98726526f",
    "Email": "6622954@gmail.com",
    "UserId": "",
    "Asin": "B0BJQQVPY2",
    "Title": "Delta 6-Setting Chrome Shower Head with High Pressure Spray, 6 Inch Round Shower He...",
    "PriceSeen": 36.86,
    "ImageUrl": "https://m.media-amazon.com/images/I/71P5dVapLnL._AC_UF480,480_SR480,480_.jpg",
    "Url": "",
    "RecordType": "RelatedProduct",
    "PrimaryAsin": "",
    "Source": "",
    "GroupId": "00000000-0000-0000-0000-000000000000",
    "TimestampUtc": "2025-11-17T23:13:54.082426Z",
    "IpAddress": "::1"
  },
  {
    "Id": "1a9b085962b444b988c706570dd8a001",
    "Email": "6622954@gmail.com",
    "UserId": "",
    "Asin": "B0DQHJR1YB",
    "Title": "High Pressure Rain Shower Head: Upgrade Shower Heads with Handheld Spray\u2026",
    "PriceSeen": 49.97,
    "ImageUrl": "https://m.media-amazon.com/images/I/810uNr8wxML._AC_UF480,480_SR480,480_.jpg",
    "Url": "",
    "RecordType": "RelatedProduct",
    "PrimaryAsin": "",
    "Source": "",
    "GroupId": "00000000-0000-0000-0000-000000000000",
    "TimestampUtc": "2025-11-17T23:13:54.0824295Z",
    "IpAddress": "::1"
  },
  {
    "Id": "51b4ea9c3947414590b6808971c2293c",
    "Email": "6622954@gmail.com",
    "UserId": "",
    "Asin": "B08975ST6P",
    "Title": "SparkPod Shower Head - High Pressure Rain - Premium Quality Luxury Design - 1-Min I...",
    "PriceSeen": 36.95,
    "ImageUrl": "https://m.media-amazon.com/images/I/71zMa-9YMBL._AC_UF480,480_SR480,480_.jpg",
    "Url": "",
    "RecordType": "RelatedProduct",
    "PrimaryAsin": "",
    "Source": "",
    "GroupId": "00000000-0000-0000-0000-000000000000",
    "TimestampUtc": "2025-11-17T23:13:54.0824361Z",
    "IpAddress": "::1"
  },
  {
    "Id": "4888d8a36c774f25afea3e942ca97105",
    "Email": "6622954@gmail.com",
    "UserId": "",
    "Asin": "B0C5B81Y8X",
    "Title": "Hotel Spa AquaCare High Pressure 8-Mode Handheld Shower Head - Anti-clog Nozzles, B...",
    "PriceSeen": 29.94,
    "ImageUrl": "https://m.media-amazon.com/images/I/91Lr056h7VL._AC_UF480,480_SR480,480_.jpg",
    "Url": "",
    "RecordType": "RelatedProduct",
    "PrimaryAsin": "",
    "Source": "",
    "GroupId": "00000000-0000-0000-0000-000000000000",
    "TimestampUtc": "2025-11-17T23:13:54.0824387Z",
    "IpAddress": "::1"
  },
  {
    "Id": "4a23ecda98d34c0496d2f84612c2492e",
    "Email": "6622954@gmail.com",
    "UserId": "",
    "Asin": "B074PR4FRT",
    "Title": "SparkPod Shower Head - High Pressure Rain - Premium Quality Luxury Design - 1-Min I...",
    "PriceSeen": 36.95,
    "ImageUrl": "https://m.media-amazon.com/images/I/81R2LXx7HNL._AC_UF480,480_SR480,480_.jpg",
    "Url": "",
    "RecordType": "RelatedProduct",
    "PrimaryAsin": "",
    "Source": "",
    "GroupId": "00000000-0000-0000-0000-000000000000",
    "TimestampUtc": "2025-11-17T23:13:54.0824412Z",
    "IpAddress": "::1"
  },
  {
    "Id": "3baa30da6a664d8ba6ccdba0d04d196f",
    "Email": "6622954@gmail.com",
    "UserId": "",
    "Asin": "B07MY4S98P",
    "Title": "NearMoon Rain Shower Head, Ultra-Thin Design-Pressure Boosting, Awesome Some Experi...",
    "PriceSeen": 19.99,
    "ImageUrl": "https://m.media-amazon.com/images/I/71cWtC\u002BRv7L._AC_UF480,480_SR480,480_.jpg",
    "Url": "",
    "RecordType": "RelatedProduct",
    "PrimaryAsin": "",
    "Source": "",
    "GroupId": "00000000-0000-0000-0000-000000000000",
    "TimestampUtc": "2025-11-17T23:13:54.0824442Z",
    "IpAddress": "::1"
  },
  {
    "Id": "47e588db49204630921e2ce43d87642d",
    "Email": "6622954@gmail.com",
    "UserId": "",
    "Asin": "B0CQ5BTYSM",
    "Title": "HOPOPRO 5-Mode High Pressure Shower Head - The Washington Post, NBC News, Today TV ...",
    "PriceSeen": 18.96,
    "ImageUrl": "https://m.media-amazon.com/images/I/61Wa1qiYA3L._AC_UF480,480_SR480,480_.jpg",
    "Url": "",
    "RecordType": "RelatedProduct",
    "PrimaryAsin": "",
    "Source": "",
    "GroupId": "00000000-0000-0000-0000-000000000000",
    "TimestampUtc": "2025-11-17T23:13:54.0824659Z",
    "IpAddress": "::1"
  },
  {
    "Id": "4695204131e0446881c448e7085d294d",
    "Email": "6622954@gmail.com",
    "UserId": "",
    "Asin": "B08SJ7V4JK",
    "Title": "(no title)",
    "PriceSeen": null,
    "ImageUrl": "https://images-na.ssl-images-amazon.com/images/G/01/x-locale/common/grey-pixel.gif",
    "Url": "",
    "RecordType": "RelatedProduct",
    "PrimaryAsin": "",
    "Source": "",
    "GroupId": "00000000-0000-0000-0000-000000000000",
    "TimestampUtc": "2025-11-17T23:13:54.0824695Z",
    "IpAddress": "::1"
  },
  {
    "Id": "b78570d5921846a79b688d52e0e3ad2a",
    "Email": "6622954@gmail.com",
    "UserId": "",
    "Asin": "B0B71RYQJZ",
    "Title": "SparkPod Shower Head - High Pressure Rain - Premium Quality Luxury Design - 1-Min I...",
    "PriceSeen": 39.95,
    "ImageUrl": "https://m.media-amazon.com/images/I/91eor8SM-ZL._AC_UF480,480_SR480,480_.jpg",
    "Url": "",
    "RecordType": "RelatedProduct",
    "PrimaryAsin": "",
    "Source": "",
    "GroupId": "00000000-0000-0000-0000-000000000000",
    "TimestampUtc": "2025-11-17T23:13:54.0824723Z",
    "IpAddress": "::1"
  },
  {
    "Id": "e7ed83150e1646fda8bbc5c690ca6c6e",
    "Email": "6622954@gmail.com",
    "UserId": "",
    "Asin": "B08QQTT6NP",
    "Title": "Luxury Rainfall Shower Head - High-Pressure showerhead Jets, rain shower head Ant-C...",
    "PriceSeen": 39.99,
    "ImageUrl": "https://m.media-amazon.com/images/I/81jCONvRyOL._AC_UF480,480_SR480,480_.jpg",
    "Url": "",
    "RecordType": "RelatedProduct",
    "PrimaryAsin": "",
    "Source": "",
    "GroupId": "00000000-0000-0000-0000-000000000000",
    "TimestampUtc": "2025-11-17T23:13:54.0825426Z",
    "IpAddress": "::1"
  },
  {
    "Id": "5ce39baaa4be40a08999a4b80697d7a6",
    "Email": "6622954@gmail.com",
    "UserId": "",
    "Asin": "B08RWTL7TB",
    "Title": "Waterfall Showerhead VMASSTONE High Pressure Showerhead - Tool Free Installation\u2026",
    "PriceSeen": 19.99,
    "ImageUrl": "https://m.media-amazon.com/images/I/717d4PujYOL._AC_UF480,480_SR480,480_.jpg",
    "Url": "",
    "RecordType": "RelatedProduct",
    "PrimaryAsin": "",
    "Source": "",
    "GroupId": "00000000-0000-0000-0000-000000000000",
    "TimestampUtc": "2025-11-17T23:13:54.082548Z",
    "IpAddress": "::1"
  },
  {
    "Id": "eeea0f697bfa4a90a573db8eaab7eed8",
    "Email": "6622954@gmail.com",
    "UserId": "",
    "Asin": "B0DZCX7YCW",
    "Title": "High Flow Filtered Shower Head, HOPOPRO 5 Modes High Pressure Fixed Showerhead with...",
    "PriceSeen": 25.99,
    "ImageUrl": "https://m.media-amazon.com/images/I/61aARbfHP2L._AC_UF480,480_SR480,480_.jpg",
    "Url": "",
    "RecordType": "RelatedProduct",
    "PrimaryAsin": "",
    "Source": "",
    "GroupId": "00000000-0000-0000-0000-000000000000",
    "TimestampUtc": "2025-11-17T23:13:54.0825512Z",
    "IpAddress": "::1"
  },
  {
    "Id": "edefcfdf01c54e8bb175b92fd0dfd98c",
    "Email": "6622954@gmail.com",
    "UserId": "",
    "Asin": "B0D6YT6BXB",
    "Title": "(no title)",
    "PriceSeen": 44.99,
    "ImageUrl": "data:image/svg\u002Bxml,%3Csvg xmlns=\u0027http://www.w3.org/2000/svg\u0027 height=\u0027100%\u0027 width=\u0027100%\u0027 preserveAspectRatio=\u0027none\u0027 /%3E",
    "Url": "",
    "RecordType": "RelatedProduct",
    "PrimaryAsin": "",
    "Source": "",
    "GroupId": "00000000-0000-0000-0000-000000000000",
    "TimestampUtc": "2025-11-17T23:13:54.0825543Z",
    "IpAddress": "::1"
  },
  {
    "Id": "0e23350973e84829b03f67ec699fd7a5",
    "Email": "6622954@gmail.com",
    "UserId": "",
    "Asin": "B09WY7CRF5",
    "Title": "(no title)",
    "PriceSeen": 87.99,
    "ImageUrl": "data:image/svg\u002Bxml,%3Csvg xmlns=\u0027http://www.w3.org/2000/svg\u0027 height=\u0027100%\u0027 width=\u0027100%\u0027 preserveAspectRatio=\u0027none\u0027 /%3E",
    "Url": "",
    "RecordType": "RelatedProduct",
    "PrimaryAsin": "",
    "Source": "",
    "GroupId": "00000000-0000-0000-0000-000000000000",
    "TimestampUtc": "2025-11-17T23:13:54.0825574Z",
    "IpAddress": "::1"
  },
  {
    "Id": "c749004a841f479da0d116840718e103",
    "Email": "6622954@gmail.com",
    "UserId": "",
    "Asin": "B0CXY82LMV",
    "Title": "(no title)",
    "PriceSeen": 129,
    "ImageUrl": "data:image/svg\u002Bxml,%3Csvg xmlns=\u0027http://www.w3.org/2000/svg\u0027 height=\u0027100%\u0027 width=\u0027100%\u0027 preserveAspectRatio=\u0027none\u0027 /%3E",
    "Url": "",
    "RecordType": "RelatedProduct",
    "PrimaryAsin": "",
    "Source": "",
    "GroupId": "00000000-0000-0000-0000-000000000000",
    "TimestampUtc": "2025-11-17T23:13:54.0825611Z",
    "IpAddress": "::1"
  },
  {
    "Id": "6bd3c31dcf7f462eb189bc677b8618f0",
    "Email": "6622954@gmail.com",
    "UserId": "",
    "Asin": "B0BC1F34JL",
    "Title": "(no title)",
    "PriceSeen": 35.5,
    "ImageUrl": "data:image/svg\u002Bxml,%3Csvg xmlns=\u0027http://www.w3.org/2000/svg\u0027 height=\u0027100%\u0027 width=\u0027100%\u0027 preserveAspectRatio=\u0027none\u0027 /%3E",
    "Url": "",
    "RecordType": "RelatedProduct",
    "PrimaryAsin": "",
    "Source": "",
    "GroupId": "00000000-0000-0000-0000-000000000000",
    "TimestampUtc": "2025-11-17T23:13:54.0825645Z",
    "IpAddress": "::1"
  },
  {
    "Id": "97e0a5bf1ac3415a8cec758da10382eb",
    "Email": "6622954@gmail.com",
    "UserId": "",
    "Asin": "B0BB5DV24G",
    "Title": "(no title)",
    "PriceSeen": 29.95,
    "ImageUrl": "data:image/svg\u002Bxml,%3Csvg xmlns=\u0027http://www.w3.org/2000/svg\u0027 height=\u0027100%\u0027 width=\u0027100%\u0027 preserveAspectRatio=\u0027none\u0027 /%3E",
    "Url": "",
    "RecordType": "RelatedProduct",
    "PrimaryAsin": "",
    "Source": "",
    "GroupId": "00000000-0000-0000-0000-000000000000",
    "TimestampUtc": "2025-11-17T23:13:54.0825677Z",
    "IpAddress": "::1"
  },
  {
    "Id": "ab804a3867054986abe1dad855b3b948",
    "Email": "6622954@gmail.com",
    "UserId": "",
    "Asin": "B082WWGCC9",
    "Title": "GURIN Shower Head High Pressure Rain Shower head - 6 Inch Luxury Design with Adjustable Angles, Anti-Clogging Nozzles, Easy 1-Min Install, Premium Chrome Finish for Bathroom (2.5 GPM)",
    "PriceSeen": 24.55,
    "ImageUrl": "https://m.media-amazon.com/images/I/7103SQvtF7L._AC_SX679_.jpg",
    "Url": "",
    "RecordType": "RelatedProduct",
    "PrimaryAsin": "",
    "Source": "",
    "GroupId": "00000000-0000-0000-0000-000000000000",
    "TimestampUtc": "2025-11-17T23:20:14.8165789Z",
    "IpAddress": "::1"
  },
  {
    "Id": "c20d312a70a14cb8843c607153936ebe",
    "Email": "6622954@gmail.com",
    "UserId": "",
    "Asin": "B07H3GJNBW",
    "Title": "High Pressure Shower Head - Anti-Clogging Silicone Nozzles - 2.5 GPM Removable Rest...",
    "PriceSeen": 43.99,
    "ImageUrl": "https://m.media-amazon.com/images/I/71MZyIyuBfL._AC_UF480,480_SR480,480_.jpg",
    "Url": "",
    "RecordType": "RelatedProduct",
    "PrimaryAsin": "",
    "Source": "",
    "GroupId": "00000000-0000-0000-0000-000000000000",
    "TimestampUtc": "2025-11-17T23:20:14.816765Z",
    "IpAddress": "::1"
  },
  {
    "Id": "4e97508cfc6c4fcf8df80d31fc538612",
    "Email": "6622954@gmail.com",
    "UserId": "",
    "Asin": "B0DN6DBL2G",
    "Title": "Shower Head High Pressure Rain Premium Quality Luxury Design Anti-Clogging Silicone...",
    "PriceSeen": 17.99,
    "ImageUrl": "https://m.media-amazon.com/images/I/61EW6Y\u002ByKmL._AC_UF480,480_SR480,480_.jpg",
    "Url": "",
    "RecordType": "RelatedProduct",
    "PrimaryAsin": "",
    "Source": "",
    "GroupId": "00000000-0000-0000-0000-000000000000",
    "TimestampUtc": "2025-11-17T23:20:14.8167845Z",
    "IpAddress": "::1"
  },
  {
    "Id": "53852c965ce24f84a101a8b3a31bcf9a",
    "Email": "6622954@gmail.com",
    "UserId": "",
    "Asin": "B08QR7PGCT",
    "Title": "Heatsistence-Luxury Rainfall Shower Head - High-Pressure showerhead Jets, rain\u2026",
    "PriceSeen": 22.99,
    "ImageUrl": "https://m.media-amazon.com/images/I/81yPbiYLIHL._AC_UF480,480_SR480,480_.jpg",
    "Url": "",
    "RecordType": "RelatedProduct",
    "PrimaryAsin": "",
    "Source": "",
    "GroupId": "00000000-0000-0000-0000-000000000000",
    "TimestampUtc": "2025-11-17T23:20:14.8177504Z",
    "IpAddress": "::1"
  },
  {
    "Id": "bf77b76120df48c0bd44d847fa1b7550",
    "Email": "6622954@gmail.com",
    "UserId": "",
    "Asin": "B0BJQQVPY2",
    "Title": "Delta 6-Setting Chrome Shower Head with High Pressure Spray, 6 Inch Round Shower He...",
    "PriceSeen": 36.86,
    "ImageUrl": "https://m.media-amazon.com/images/I/71P5dVapLnL._AC_UF480,480_SR480,480_.jpg",
    "Url": "",
    "RecordType": "RelatedProduct",
    "PrimaryAsin": "",
    "Source": "",
    "GroupId": "00000000-0000-0000-0000-000000000000",
    "TimestampUtc": "2025-11-17T23:20:14.8177771Z",
    "IpAddress": "::1"
  },
  {
    "Id": "7a1b3f176515441f82c6ef766b1de4ef",
    "Email": "6622954@gmail.com",
    "UserId": "",
    "Asin": "B0DQHJR1YB",
    "Title": "High Pressure Rain Shower Head: Upgrade Shower Heads with Handheld Spray\u2026",
    "PriceSeen": 49.97,
    "ImageUrl": "https://m.media-amazon.com/images/I/810uNr8wxML._AC_UF480,480_SR480,480_.jpg",
    "Url": "",
    "RecordType": "RelatedProduct",
    "PrimaryAsin": "",
    "Source": "",
    "GroupId": "00000000-0000-0000-0000-000000000000",
    "TimestampUtc": "2025-11-17T23:20:14.8177814Z",
    "IpAddress": "::1"
  },
  {
    "Id": "dc6c4a5c6ef64a5091efeee329a83fac",
    "Email": "6622954@gmail.com",
    "UserId": "",
    "Asin": "B08975ST6P",
    "Title": "SparkPod Shower Head - High Pressure Rain - Premium Quality Luxury Design - 1-Min I...",
    "PriceSeen": 36.95,
    "ImageUrl": "https://m.media-amazon.com/images/I/71zMa-9YMBL._AC_UF480,480_SR480,480_.jpg",
    "Url": "",
    "RecordType": "RelatedProduct",
    "PrimaryAsin": "",
    "Source": "",
    "GroupId": "00000000-0000-0000-0000-000000000000",
    "TimestampUtc": "2025-11-17T23:20:14.8177865Z",
    "IpAddress": "::1"
  },
  {
    "Id": "290379b263554331bf9e2284f948a00f",
    "Email": "6622954@gmail.com",
    "UserId": "",
    "Asin": "B0C5B81Y8X",
    "Title": "Hotel Spa AquaCare High Pressure 8-Mode Handheld Shower Head - Anti-clog Nozzles, B...",
    "PriceSeen": 29.94,
    "ImageUrl": "https://m.media-amazon.com/images/I/91Lr056h7VL._AC_UF480,480_SR480,480_.jpg",
    "Url": "",
    "RecordType": "RelatedProduct",
    "PrimaryAsin": "",
    "Source": "",
    "GroupId": "00000000-0000-0000-0000-000000000000",
    "TimestampUtc": "2025-11-17T23:20:14.8177894Z",
    "IpAddress": "::1"
  },
  {
    "Id": "1c5118452fcc470eae5c404829f129c1",
    "Email": "6622954@gmail.com",
    "UserId": "",
    "Asin": "B074PR4FRT",
    "Title": "SparkPod Shower Head - High Pressure Rain - Premium Quality Luxury Design - 1-Min I...",
    "PriceSeen": 36.95,
    "ImageUrl": "https://m.media-amazon.com/images/I/81R2LXx7HNL._AC_UF480,480_SR480,480_.jpg",
    "Url": "",
    "RecordType": "RelatedProduct",
    "PrimaryAsin": "",
    "Source": "",
    "GroupId": "00000000-0000-0000-0000-000000000000",
    "TimestampUtc": "2025-11-17T23:20:14.8177932Z",
    "IpAddress": "::1"
  },
  {
    "Id": "3647ffda1709450aadd6dc0bf7df8932",
    "Email": "6622954@gmail.com",
    "UserId": "",
    "Asin": "B07MY4S98P",
    "Title": "NearMoon Rain Shower Head, Ultra-Thin Design-Pressure Boosting, Awesome Some Experi...",
    "PriceSeen": 19.99,
    "ImageUrl": "https://m.media-amazon.com/images/I/71cWtC\u002BRv7L._AC_UF480,480_SR480,480_.jpg",
    "Url": "",
    "RecordType": "RelatedProduct",
    "PrimaryAsin": "",
    "Source": "",
    "GroupId": "00000000-0000-0000-0000-000000000000",
    "TimestampUtc": "2025-11-17T23:20:14.8177965Z",
    "IpAddress": "::1"
  },
  {
    "Id": "1e6bf95673b44ceeafc49d790682df5b",
    "Email": "6622954@gmail.com",
    "UserId": "",
    "Asin": "B0CQ5BTYSM",
    "Title": "HOPOPRO 5-Mode High Pressure Shower Head - The Washington Post, NBC News, Today TV ...",
    "PriceSeen": 18.96,
    "ImageUrl": "https://m.media-amazon.com/images/I/61Wa1qiYA3L._AC_UF480,480_SR480,480_.jpg",
    "Url": "",
    "RecordType": "RelatedProduct",
    "PrimaryAsin": "",
    "Source": "",
    "GroupId": "00000000-0000-0000-0000-000000000000",
    "TimestampUtc": "2025-11-17T23:20:14.8178004Z",
    "IpAddress": "::1"
  },
  {
    "Id": "80132fc4b21b4204bed935b20deed376",
    "Email": "6622954@gmail.com",
    "UserId": "",
    "Asin": "B08SJ7V4JK",
    "Title": "(no title)",
    "PriceSeen": null,
    "ImageUrl": "https://images-na.ssl-images-amazon.com/images/G/01/x-locale/common/grey-pixel.gif",
    "Url": "",
    "RecordType": "RelatedProduct",
    "PrimaryAsin": "",
    "Source": "",
    "GroupId": "00000000-0000-0000-0000-000000000000",
    "TimestampUtc": "2025-11-17T23:20:14.8178036Z",
    "IpAddress": "::1"
  },
  {
    "Id": "3859a687db574fcdb210f6768c0aa54f",
    "Email": "6622954@gmail.com",
    "UserId": "",
    "Asin": "B0B71RYQJZ",
    "Title": "SparkPod Shower Head - High Pressure Rain - Premium Quality Luxury Design - 1-Min I...",
    "PriceSeen": 39.95,
    "ImageUrl": "https://m.media-amazon.com/images/I/91eor8SM-ZL._AC_UF480,480_SR480,480_.jpg",
    "Url": "",
    "RecordType": "RelatedProduct",
    "PrimaryAsin": "",
    "Source": "",
    "GroupId": "00000000-0000-0000-0000-000000000000",
    "TimestampUtc": "2025-11-17T23:20:14.817807Z",
    "IpAddress": "::1"
  },
  {
    "Id": "de857e8901524058aa60cfff039a97f3",
    "Email": "6622954@gmail.com",
    "UserId": "",
    "Asin": "B08QQTT6NP",
    "Title": "Luxury Rainfall Shower Head - High-Pressure showerhead Jets, rain shower head Ant-C...",
    "PriceSeen": 39.99,
    "ImageUrl": "https://m.media-amazon.com/images/I/81jCONvRyOL._AC_UF480,480_SR480,480_.jpg",
    "Url": "",
    "RecordType": "RelatedProduct",
    "PrimaryAsin": "",
    "Source": "",
    "GroupId": "00000000-0000-0000-0000-000000000000",
    "TimestampUtc": "2025-11-17T23:20:14.8178168Z",
    "IpAddress": "::1"
  },
  {
    "Id": "f65db034fc104a26bc9d36414b98e401",
    "Email": "6622954@gmail.com",
    "UserId": "",
    "Asin": "B08RWTL7TB",
    "Title": "Waterfall Showerhead VMASSTONE High Pressure Showerhead - Tool Free Installation\u2026",
    "PriceSeen": 19.99,
    "ImageUrl": "https://m.media-amazon.com/images/I/717d4PujYOL._AC_UF480,480_SR480,480_.jpg",
    "Url": "",
    "RecordType": "RelatedProduct",
    "PrimaryAsin": "",
    "Source": "",
    "GroupId": "00000000-0000-0000-0000-000000000000",
    "TimestampUtc": "2025-11-17T23:20:14.8178201Z",
    "IpAddress": "::1"
  },
  {
    "Id": "0265b40ad2e94cdb8a4535e079e27904",
    "Email": "6622954@gmail.com",
    "UserId": "",
    "Asin": "B0DZCX7YCW",
    "Title": "High Flow Filtered Shower Head, HOPOPRO 5 Modes High Pressure Fixed Showerhead with...",
    "PriceSeen": 25.99,
    "ImageUrl": "https://m.media-amazon.com/images/I/61aARbfHP2L._AC_UF480,480_SR480,480_.jpg",
    "Url": "",
    "RecordType": "RelatedProduct",
    "PrimaryAsin": "",
    "Source": "",
    "GroupId": "00000000-0000-0000-0000-000000000000",
    "TimestampUtc": "2025-11-17T23:20:14.8178233Z",
    "IpAddress": "::1"
  },
  {
    "Id": "f0d94689e2a04cdb900fadcbdc21f18d",
    "Email": "6622954@gmail.com",
    "UserId": "",
    "Asin": "B0D6YT6BXB",
    "Title": "(no title)",
    "PriceSeen": 44.99,
    "ImageUrl": "data:image/svg\u002Bxml,%3Csvg xmlns=\u0027http://www.w3.org/2000/svg\u0027 height=\u0027100%\u0027 width=\u0027100%\u0027 preserveAspectRatio=\u0027none\u0027 /%3E",
    "Url": "",
    "RecordType": "RelatedProduct",
    "PrimaryAsin": "",
    "Source": "",
    "GroupId": "00000000-0000-0000-0000-000000000000",
    "TimestampUtc": "2025-11-17T23:20:14.8178266Z",
    "IpAddress": "::1"
  },
  {
    "Id": "97a7f7c19dea427cb31b76db775d1faf",
    "Email": "6622954@gmail.com",
    "UserId": "",
    "Asin": "B09WY7CRF5",
    "Title": "(no title)",
    "PriceSeen": 87.99,
    "ImageUrl": "data:image/svg\u002Bxml,%3Csvg xmlns=\u0027http://www.w3.org/2000/svg\u0027 height=\u0027100%\u0027 width=\u0027100%\u0027 preserveAspectRatio=\u0027none\u0027 /%3E",
    "Url": "",
    "RecordType": "RelatedProduct",
    "PrimaryAsin": "",
    "Source": "",
    "GroupId": "00000000-0000-0000-0000-000000000000",
    "TimestampUtc": "2025-11-17T23:20:14.8178301Z",
    "IpAddress": "::1"
  },
  {
    "Id": "9e8dfdd160f24af6ae3743d790f9b37c",
    "Email": "6622954@gmail.com",
    "UserId": "",
    "Asin": "B0CXY82LMV",
    "Title": "(no title)",
    "PriceSeen": 129,
    "ImageUrl": "data:image/svg\u002Bxml,%3Csvg xmlns=\u0027http://www.w3.org/2000/svg\u0027 height=\u0027100%\u0027 width=\u0027100%\u0027 preserveAspectRatio=\u0027none\u0027 /%3E",
    "Url": "",
    "RecordType": "RelatedProduct",
    "PrimaryAsin": "",
    "Source": "",
    "GroupId": "00000000-0000-0000-0000-000000000000",
    "TimestampUtc": "2025-11-17T23:20:14.8178334Z",
    "IpAddress": "::1"
  },
  {
    "Id": "86f4fbf2642b42c5859b1baf1b167a3d",
    "Email": "6622954@gmail.com",
    "UserId": "",
    "Asin": "B0BC1F34JL",
    "Title": "(no title)",
    "PriceSeen": 35.5,
    "ImageUrl": "data:image/svg\u002Bxml,%3Csvg xmlns=\u0027http://www.w3.org/2000/svg\u0027 height=\u0027100%\u0027 width=\u0027100%\u0027 preserveAspectRatio=\u0027none\u0027 /%3E",
    "Url": "",
    "RecordType": "RelatedProduct",
    "PrimaryAsin": "",
    "Source": "",
    "GroupId": "00000000-0000-0000-0000-000000000000",
    "TimestampUtc": "2025-11-17T23:20:14.817849Z",
    "IpAddress": "::1"
  },
  {
    "Id": "7fd366acc5954935a16f5ef64e463c46",
    "Email": "6622954@gmail.com",
    "UserId": "",
    "Asin": "B0BB5DV24G",
    "Title": "(no title)",
    "PriceSeen": 29.95,
    "ImageUrl": "data:image/svg\u002Bxml,%3Csvg xmlns=\u0027http://www.w3.org/2000/svg\u0027 height=\u0027100%\u0027 width=\u0027100%\u0027 preserveAspectRatio=\u0027none\u0027 /%3E",
    "Url": "",
    "RecordType": "RelatedProduct",
    "PrimaryAsin": "",
    "Source": "",
    "GroupId": "00000000-0000-0000-0000-000000000000",
    "TimestampUtc": "2025-11-17T23:20:14.8178532Z",
    "IpAddress": "::1"
  },
  {
    "Id": "16c92800993c40dfb226a60e72a9d898",
    "Email": "6622954@gmail.com",
    "UserId": "",
    "Asin": "B082WWGCC9",
    "Title": "GURIN Shower Head High Pressure Rain Shower head - 6 Inch Luxury Design with Adjustable Angles, Anti-Clogging Nozzles, Easy 1-Min Install, Premium Chrome Finish for Bathroom (2.5 GPM)",
    "PriceSeen": 24.55,
    "ImageUrl": "https://m.media-amazon.com/images/I/7103SQvtF7L._AC_SX679_.jpg",
    "Url": "",
    "RecordType": "PrimaryProduct",
    "PrimaryAsin": "",
    "Source": "",
    "GroupId": "00000000-0000-0000-0000-000000000000",
    "TimestampUtc": "2025-11-17T23:26:28.8809111Z",
    "IpAddress": "::1"
  },
  {
    "Id": "e3fa8f6774e444eeb16b5fc440a14c4b",
    "Email": "6622954@gmail.com",
    "UserId": "",
    "Asin": "B082WWGCC9",
    "Title": "GURIN Shower Head High Pressure Rain Shower head - 6 Inch Luxury Design with Adjustable Angles, Anti-Clogging Nozzles, Easy 1-Min Install, Premium Chrome Finish for Bathroom (2.5 GPM)",
    "PriceSeen": 24.55,
    "ImageUrl": "https://m.media-amazon.com/images/I/7103SQvtF7L._AC_SX679_.jpg",
    "Url": "",
    "RecordType": "RelatedProduct",
    "PrimaryAsin": "",
    "Source": "",
    "GroupId": "00000000-0000-0000-0000-000000000000",
    "TimestampUtc": "2025-11-17T23:26:38.6810397Z",
    "IpAddress": "::1"
  },
  {
    "Id": "25211d3396ee44acb9d195a2583cc6ad",
    "Email": "6622954@gmail.com",
    "UserId": "",
    "Asin": "B07H3GJNBW",
    "Title": "High Pressure Shower Head - Anti-Clogging Silicone Nozzles - 2.5 GPM Removable Rest...",
    "PriceSeen": 43.99,
    "ImageUrl": "https://m.media-amazon.com/images/I/71MZyIyuBfL._AC_UF480,480_SR480,480_.jpg",
    "Url": "",
    "RecordType": "RelatedProduct",
    "PrimaryAsin": "",
    "Source": "",
    "GroupId": "00000000-0000-0000-0000-000000000000",
    "TimestampUtc": "2025-11-17T23:26:38.6810624Z",
    "IpAddress": "::1"
  },
  {
    "Id": "df6e59437e7c4353b612c3da55bf8287",
    "Email": "6622954@gmail.com",
    "UserId": "",
    "Asin": "B0DN6DBL2G",
    "Title": "Shower Head High Pressure Rain Premium Quality Luxury Design Anti-Clogging Silicone...",
    "PriceSeen": 17.99,
    "ImageUrl": "https://m.media-amazon.com/images/I/61EW6Y\u002ByKmL._AC_UF480,480_SR480,480_.jpg",
    "Url": "",
    "RecordType": "RelatedProduct",
    "PrimaryAsin": "",
    "Source": "",
    "GroupId": "00000000-0000-0000-0000-000000000000",
    "TimestampUtc": "2025-11-17T23:26:38.6810702Z",
    "IpAddress": "::1"
  },
  {
    "Id": "e7252331f9fe49bdafd50792e917d8a7",
    "Email": "6622954@gmail.com",
    "UserId": "",
    "Asin": "B08QR7PGCT",
    "Title": "Heatsistence-Luxury Rainfall Shower Head - High-Pressure showerhead Jets, rain\u2026",
    "PriceSeen": 22.99,
    "ImageUrl": "https://m.media-amazon.com/images/I/81yPbiYLIHL._AC_UF480,480_SR480,480_.jpg",
    "Url": "",
    "RecordType": "RelatedProduct",
    "PrimaryAsin": "",
    "Source": "",
    "GroupId": "00000000-0000-0000-0000-000000000000",
    "TimestampUtc": "2025-11-17T23:26:38.681078Z",
    "IpAddress": "::1"
  },
  {
    "Id": "0c86b5ed1e2b468eaf576e5bec601cd4",
    "Email": "6622954@gmail.com",
    "UserId": "",
    "Asin": "B0BJQQVPY2",
    "Title": "Delta 6-Setting Chrome Shower Head with High Pressure Spray, 6 Inch Round Shower He...",
    "PriceSeen": 36.86,
    "ImageUrl": "https://m.media-amazon.com/images/I/71P5dVapLnL._AC_UF480,480_SR480,480_.jpg",
    "Url": "",
    "RecordType": "RelatedProduct",
    "PrimaryAsin": "",
    "Source": "",
    "GroupId": "00000000-0000-0000-0000-000000000000",
    "TimestampUtc": "2025-11-17T23:26:38.6810857Z",
    "IpAddress": "::1"
  },
  {
    "Id": "7dc8bdd2d3c54cb09492f9f09213bd3c",
    "Email": "6622954@gmail.com",
    "UserId": "",
    "Asin": "B0DQHJR1YB",
    "Title": "High Pressure Rain Shower Head: Upgrade Shower Heads with Handheld Spray\u2026",
    "PriceSeen": 49.97,
    "ImageUrl": "https://m.media-amazon.com/images/I/810uNr8wxML._AC_UF480,480_SR480,480_.jpg",
    "Url": "",
    "RecordType": "RelatedProduct",
    "PrimaryAsin": "",
    "Source": "",
    "GroupId": "00000000-0000-0000-0000-000000000000",
    "TimestampUtc": "2025-11-17T23:26:38.6810939Z",
    "IpAddress": "::1"
  },
  {
    "Id": "69f40b3367e948b4ae5278f0ab037c33",
    "Email": "6622954@gmail.com",
    "UserId": "",
    "Asin": "B08975ST6P",
    "Title": "SparkPod Shower Head - High Pressure Rain - Premium Quality Luxury Design - 1-Min I...",
    "PriceSeen": 36.95,
    "ImageUrl": "https://m.media-amazon.com/images/I/71zMa-9YMBL._AC_UF480,480_SR480,480_.jpg",
    "Url": "",
    "RecordType": "RelatedProduct",
    "PrimaryAsin": "",
    "Source": "",
    "GroupId": "00000000-0000-0000-0000-000000000000",
    "TimestampUtc": "2025-11-17T23:26:38.6811018Z",
    "IpAddress": "::1"
  },
  {
    "Id": "f46105989a1a46eb956b7023cfdf2410",
    "Email": "6622954@gmail.com",
    "UserId": "",
    "Asin": "B0C5B81Y8X",
    "Title": "Hotel Spa AquaCare High Pressure 8-Mode Handheld Shower Head - Anti-clog Nozzles, B...",
    "PriceSeen": 29.94,
    "ImageUrl": "https://m.media-amazon.com/images/I/91Lr056h7VL._AC_UF480,480_SR480,480_.jpg",
    "Url": "",
    "RecordType": "RelatedProduct",
    "PrimaryAsin": "",
    "Source": "",
    "GroupId": "00000000-0000-0000-0000-000000000000",
    "TimestampUtc": "2025-11-17T23:26:38.6811096Z",
    "IpAddress": "::1"
  },
  {
    "Id": "9d1f116402e340f09b8cb958ea8d6ce2",
    "Email": "6622954@gmail.com",
    "UserId": "",
    "Asin": "B074PR4FRT",
    "Title": "SparkPod Shower Head - High Pressure Rain - Premium Quality Luxury Design - 1-Min I...",
    "PriceSeen": 36.95,
    "ImageUrl": "https://m.media-amazon.com/images/I/81R2LXx7HNL._AC_UF480,480_SR480,480_.jpg",
    "Url": "",
    "RecordType": "RelatedProduct",
    "PrimaryAsin": "",
    "Source": "",
    "GroupId": "00000000-0000-0000-0000-000000000000",
    "TimestampUtc": "2025-11-17T23:26:38.6811439Z",
    "IpAddress": "::1"
  },
  {
    "Id": "fa173b4ec5f541af9a6cd3138a387ed6",
    "Email": "6622954@gmail.com",
    "UserId": "",
    "Asin": "B07MY4S98P",
    "Title": "NearMoon Rain Shower Head, Ultra-Thin Design-Pressure Boosting, Awesome Some Experi...",
    "PriceSeen": 19.99,
    "ImageUrl": "https://m.media-amazon.com/images/I/71cWtC\u002BRv7L._AC_UF480,480_SR480,480_.jpg",
    "Url": "",
    "RecordType": "RelatedProduct",
    "PrimaryAsin": "",
    "Source": "",
    "GroupId": "00000000-0000-0000-0000-000000000000",
    "TimestampUtc": "2025-11-17T23:26:38.681153Z",
    "IpAddress": "::1"
  },
  {
    "Id": "c3a132572b164eb39660eec0047e89ec",
    "Email": "6622954@gmail.com",
    "UserId": "",
    "Asin": "B0CQ5BTYSM",
    "Title": "HOPOPRO 5-Mode High Pressure Shower Head - The Washington Post, NBC News, Today TV ...",
    "PriceSeen": 18.96,
    "ImageUrl": "https://m.media-amazon.com/images/I/61Wa1qiYA3L._AC_UF480,480_SR480,480_.jpg",
    "Url": "",
    "RecordType": "RelatedProduct",
    "PrimaryAsin": "",
    "Source": "",
    "GroupId": "00000000-0000-0000-0000-000000000000",
    "TimestampUtc": "2025-11-17T23:26:38.6811611Z",
    "IpAddress": "::1"
  },
  {
    "Id": "b051e81be25b4e50b971ff78c85494c5",
    "Email": "6622954@gmail.com",
    "UserId": "",
    "Asin": "B08SJ7V4JK",
    "Title": "(no title)",
    "PriceSeen": null,
    "ImageUrl": "https://images-na.ssl-images-amazon.com/images/G/01/x-locale/common/grey-pixel.gif",
    "Url": "",
    "RecordType": "RelatedProduct",
    "PrimaryAsin": "",
    "Source": "",
    "GroupId": "00000000-0000-0000-0000-000000000000",
    "TimestampUtc": "2025-11-17T23:26:38.6811693Z",
    "IpAddress": "::1"
  },
  {
    "Id": "815197fdcdc949a6ae310a8015bdaf81",
    "Email": "6622954@gmail.com",
    "UserId": "",
    "Asin": "B0B71RYQJZ",
    "Title": "SparkPod Shower Head - High Pressure Rain - Premium Quality Luxury Design - 1-Min I...",
    "PriceSeen": 39.95,
    "ImageUrl": "https://m.media-amazon.com/images/I/91eor8SM-ZL._AC_UF480,480_SR480,480_.jpg",
    "Url": "",
    "RecordType": "RelatedProduct",
    "PrimaryAsin": "",
    "Source": "",
    "GroupId": "00000000-0000-0000-0000-000000000000",
    "TimestampUtc": "2025-11-17T23:26:38.6811777Z",
    "IpAddress": "::1"
  },
  {
    "Id": "bc000948ed76467da05e82c6a613d82a",
    "Email": "6622954@gmail.com",
    "UserId": "",
    "Asin": "B08QQTT6NP",
    "Title": "Luxury Rainfall Shower Head - High-Pressure showerhead Jets, rain shower head Ant-C...",
    "PriceSeen": 39.99,
    "ImageUrl": "https://m.media-amazon.com/images/I/81jCONvRyOL._AC_UF480,480_SR480,480_.jpg",
    "Url": "",
    "RecordType": "RelatedProduct",
    "PrimaryAsin": "",
    "Source": "",
    "GroupId": "00000000-0000-0000-0000-000000000000",
    "TimestampUtc": "2025-11-17T23:26:38.681186Z",
    "IpAddress": "::1"
  },
  {
    "Id": "feeaed386ad743338340812e19b68206",
    "Email": "6622954@gmail.com",
    "UserId": "",
    "Asin": "B08RWTL7TB",
    "Title": "Waterfall Showerhead VMASSTONE High Pressure Showerhead - Tool Free Installation\u2026",
    "PriceSeen": 19.99,
    "ImageUrl": "https://m.media-amazon.com/images/I/717d4PujYOL._AC_UF480,480_SR480,480_.jpg",
    "Url": "",
    "RecordType": "RelatedProduct",
    "PrimaryAsin": "",
    "Source": "",
    "GroupId": "00000000-0000-0000-0000-000000000000",
    "TimestampUtc": "2025-11-17T23:26:38.6811945Z",
    "IpAddress": "::1"
  },
  {
    "Id": "3e74cc02fb9e4603bb7fb0ceab5704fa",
    "Email": "6622954@gmail.com",
    "UserId": "",
    "Asin": "B0DZCX7YCW",
    "Title": "High Flow Filtered Shower Head, HOPOPRO 5 Modes High Pressure Fixed Showerhead with...",
    "PriceSeen": 25.99,
    "ImageUrl": "https://m.media-amazon.com/images/I/61aARbfHP2L._AC_UF480,480_SR480,480_.jpg",
    "Url": "",
    "RecordType": "RelatedProduct",
    "PrimaryAsin": "",
    "Source": "",
    "GroupId": "00000000-0000-0000-0000-000000000000",
    "TimestampUtc": "2025-11-17T23:26:38.6812049Z",
    "IpAddress": "::1"
  },
  {
    "Id": "5b23da9e950c47c8af111bf782c9d36a",
    "Email": "6622954@gmail.com",
    "UserId": "",
    "Asin": "B0D6YT6BXB",
    "Title": "(no title)",
    "PriceSeen": 44.99,
    "ImageUrl": "data:image/svg\u002Bxml,%3Csvg xmlns=\u0027http://www.w3.org/2000/svg\u0027 height=\u0027100%\u0027 width=\u0027100%\u0027 preserveAspectRatio=\u0027none\u0027 /%3E",
    "Url": "",
    "RecordType": "RelatedProduct",
    "PrimaryAsin": "",
    "Source": "",
    "GroupId": "00000000-0000-0000-0000-000000000000",
    "TimestampUtc": "2025-11-17T23:26:38.6812141Z",
    "IpAddress": "::1"
  },
  {
    "Id": "5cb6f9626b134a8f940eb6c262fec2e0",
    "Email": "6622954@gmail.com",
    "UserId": "",
    "Asin": "B09WY7CRF5",
    "Title": "(no title)",
    "PriceSeen": 87.99,
    "ImageUrl": "data:image/svg\u002Bxml,%3Csvg xmlns=\u0027http://www.w3.org/2000/svg\u0027 height=\u0027100%\u0027 width=\u0027100%\u0027 preserveAspectRatio=\u0027none\u0027 /%3E",
    "Url": "",
    "RecordType": "RelatedProduct",
    "PrimaryAsin": "",
    "Source": "",
    "GroupId": "00000000-0000-0000-0000-000000000000",
    "TimestampUtc": "2025-11-17T23:26:38.681223Z",
    "IpAddress": "::1"
  },
  {
    "Id": "5bd7f39495c84811b26b93ca655a7d03",
    "Email": "6622954@gmail.com",
    "UserId": "",
    "Asin": "B0CXY82LMV",
    "Title": "(no title)",
    "PriceSeen": 129,
    "ImageUrl": "data:image/svg\u002Bxml,%3Csvg xmlns=\u0027http://www.w3.org/2000/svg\u0027 height=\u0027100%\u0027 width=\u0027100%\u0027 preserveAspectRatio=\u0027none\u0027 /%3E",
    "Url": "",
    "RecordType": "RelatedProduct",
    "PrimaryAsin": "",
    "Source": "",
    "GroupId": "00000000-0000-0000-0000-000000000000",
    "TimestampUtc": "2025-11-17T23:26:38.6812438Z",
    "IpAddress": "::1"
  },
  {
    "Id": "d38b49659ceb4dea988a5a1d5cd4a390",
    "Email": "6622954@gmail.com",
    "UserId": "",
    "Asin": "B0BC1F34JL",
    "Title": "(no title)",
    "PriceSeen": 35.5,
    "ImageUrl": "data:image/svg\u002Bxml,%3Csvg xmlns=\u0027http://www.w3.org/2000/svg\u0027 height=\u0027100%\u0027 width=\u0027100%\u0027 preserveAspectRatio=\u0027none\u0027 /%3E",
    "Url": "",
    "RecordType": "RelatedProduct",
    "PrimaryAsin": "",
    "Source": "",
    "GroupId": "00000000-0000-0000-0000-000000000000",
    "TimestampUtc": "2025-11-17T23:26:38.681253Z",
    "IpAddress": "::1"
  },
  {
    "Id": "65cd7bbcaab24be49302402e392fb71f",
    "Email": "6622954@gmail.com",
    "UserId": "",
    "Asin": "B0BB5DV24G",
    "Title": "(no title)",
    "PriceSeen": 29.95,
    "ImageUrl": "data:image/svg\u002Bxml,%3Csvg xmlns=\u0027http://www.w3.org/2000/svg\u0027 height=\u0027100%\u0027 width=\u0027100%\u0027 preserveAspectRatio=\u0027none\u0027 /%3E",
    "Url": "",
    "RecordType": "RelatedProduct",
    "PrimaryAsin": "",
    "Source": "",
    "GroupId": "00000000-0000-0000-0000-000000000000",
    "TimestampUtc": "2025-11-17T23:26:38.6812619Z",
    "IpAddress": "::1"
  },
  {
    "Id": "45cba032272f4362aaaa5807a190267f",
    "Email": "6622954@gmail.com",
    "UserId": "",
    "Asin": "B082WWGCC9",
    "Title": "GURIN Shower Head High Pressure Rain Shower head - 6 Inch Luxury Design with Adjustable Angles, Anti-Clogging Nozzles, Easy 1-Min Install, Premium Chrome Finish for Bathroom (2.5 GPM)",
    "PriceSeen": 24.55,
    "ImageUrl": "https://m.media-amazon.com/images/I/7103SQvtF7L._AC_SX679_.jpg",
    "Url": "",
    "RecordType": "PrimaryProduct",
    "PrimaryAsin": "",
    "Source": "",
    "GroupId": "00000000-0000-0000-0000-000000000000",
    "TimestampUtc": "2025-11-18T15:24:48.2001585Z",
    "IpAddress": "::1"
  },
  {
    "Id": "442f598373f74557b70c875d760a4629",
    "Email": "6622954@gmail.com",
    "UserId": "",
    "Asin": "B07MY4S98P",
    "Title": "NearMoon Rain Shower Head, Ultra-Thin Design-Pressure Boosting, Awesome Some Experience, High Flow Stainless Steel Rainfall Head (8 Inch,Chrome Finish)",
    "PriceSeen": 19.99,
    "ImageUrl": "https://m.media-amazon.com/images/I/71cWtC\u002BRv7L._AC_SX679_.jpg",
    "Url": "",
    "RecordType": "PrimaryProduct",
    "PrimaryAsin": "",
    "Source": "",
    "GroupId": "13f3ad76-32de-4505-90d0-0659dd2657e1",
    "TimestampUtc": "2025-11-18T18:35:03.5589118Z",
    "IpAddress": "::1"
  },
  {
    "Id": "52845b86a1814ee3b76c7936be9705b5",
    "Email": "6622954@gmail.com",
    "UserId": "",
    "Asin": "B07MY4S98P",
    "Title": "NearMoon Rain Shower Head, Ultra-Thin Design-Pressure Boosting, Awesome Some Experience, High Flow Stainless Steel Rainfall Head (8 Inch,Chrome Finish)",
    "PriceSeen": 19.99,
    "ImageUrl": "https://m.media-amazon.com/images/I/71cWtC\u002BRv7L._AC_SX679_.jpg",
    "Url": "",
    "RecordType": "PrimaryProduct",
    "PrimaryAsin": "",
    "Source": "",
    "GroupId": "666e389f-e751-49ba-a102-0ef577650b48",
    "TimestampUtc": "2025-11-18T18:48:53.3146521Z",
    "IpAddress": "::1"
  }
]